<?xml version="1.0" encoding="UTF-8" standalone="yes"?>
<DatabaseModel VersionId="2.4">
    <Name></Name>
    <Description></Description>
    <DatabaseEngine>
        <Name>oracle</Name>
        <Version>21c</Version>
    </DatabaseEngine>
    <Counters>
        <Counter>
            <Name>table</Name>
            <Value>20</Value>
            <Prefix>t</Prefix>
        </Counter>
        <Counter>
            <Name>external_table</Name>
            <Value>0</Value>
            <Prefix>et</Prefix>
        </Counter>
        <Counter>
            <Name>column</Name>
            <Value>66</Value>
            <Prefix>c</Prefix>
        </Counter>
        <Counter>
            <Name>external_table_column</Name>
            <Value>0</Value>
            <Prefix>etc</Prefix>
        </Counter>
        <Counter>
            <Name>index</Name>
            <Value>0</Value>
            <Prefix>i</Prefix>
        </Counter>
        <Counter>
            <Name>reference</Name>
            <Value>27</Value>
            <Prefix>r</Prefix>
        </Counter>
        <Counter>
            <Name>table_check</Name>
            <Value>2</Value>
            <Prefix>tc</Prefix>
        </Counter>
        <Counter>
            <Name>alternate_key</Name>
            <Value>0</Value>
            <Prefix>a</Prefix>
        </Counter>
        <Counter>
            <Name>sequence</Name>
            <Value>0</Value>
            <Prefix>s</Prefix>
        </Counter>
        <Counter>
            <Name>note</Name>
            <Value>2</Value>
            <Prefix>n</Prefix>
        </Counter>
        <Counter>
            <Name>view</Name>
            <Value>0</Value>
            <Prefix>v</Prefix>
        </Counter>
        <Counter>
            <Name>view_column</Name>
            <Value>0</Value>
            <Prefix>vc</Prefix>
        </Counter>
        <Counter>
            <Name>materialized_view</Name>
            <Value>0</Value>
            <Prefix>mv</Prefix>
        </Counter>
        <Counter>
            <Name>materialized_view_column</Name>
            <Value>0</Value>
            <Prefix>mvc</Prefix>
        </Counter>
        <Counter>
            <Name>area</Name>
            <Value>0</Value>
            <Prefix>ar</Prefix>
        </Counter>
        <Counter>
            <Name>text</Name>
            <Value>0</Value>
            <Prefix>tx</Prefix>
        </Counter>
        <Counter>
            <Name>tableDisplay</Name>
            <Value>20</Value>
            <Prefix>td</Prefix>
        </Counter>
        <Counter>
            <Name>externalTableDisplay</Name>
            <Value>0</Value>
            <Prefix>etd</Prefix>
        </Counter>
        <Counter>
            <Name>viewDisplay</Name>
            <Value>0</Value>
            <Prefix>vd</Prefix>
        </Counter>
        <Counter>
            <Name>materializedViewDisplay</Name>
            <Value>0</Value>
            <Prefix>mvd</Prefix>
        </Counter>
        <Counter>
            <Name>referenceDisplay</Name>
            <Value>27</Value>
            <Prefix>rd</Prefix>
        </Counter>
    </Counters>
    <AdditionalSQLBeforeCreate></AdditionalSQLBeforeCreate>
    <AdditionalSQLAfterCreate></AdditionalSQLAfterCreate>
    <AdditionalSQLBeforeDrop></AdditionalSQLBeforeDrop>
    <AdditionalSQLAfterDrop></AdditionalSQLAfterDrop>
    <Tables>
        <Table Id="t1">
            <Name>Podwladny</Name>
            <Description></Description>
            <Columns>
                <Column Id="c8">
                    <Name>Osoba_ID</Name>
                    <Type>integer</Type>
                    <Description></Description>
                    <Nullable>false</Nullable>
                    <DefaultValue></DefaultValue>
                    <CheckExpression></CheckExpression>
                    <Properties/>
                </Column>
            </Columns>
            <PrimaryKey>
                <Name></Name>
                <Columns>
                    <Column>c8</Column>
                </Columns>
            </PrimaryKey>
            <AlternateKeys/>
            <Indexes/>
            <TableChecks/>
            <AdditionalSQLBefore></AdditionalSQLBefore>
            <AdditionalSQLAfter></AdditionalSQLAfter>
            <Properties/>
        </Table>
        <Table Id="t2">
            <Name>Osoba</Name>
            <Description></Description>
            <Columns>
                <Column Id="c1">
                    <Name>ID</Name>
                    <Type>integer</Type>
                    <Description></Description>
                    <Nullable>false</Nullable>
                    <DefaultValue></DefaultValue>
                    <CheckExpression></CheckExpression>
                    <Properties/>
                </Column>
                <Column Id="c2">
                    <Name>Imie</Name>
                    <Type>varchar2(30)</Type>
                    <Description></Description>
                    <Nullable>false</Nullable>
                    <DefaultValue></DefaultValue>
                    <CheckExpression></CheckExpression>
                    <Properties/>
                </Column>
                <Column Id="c66">
                    <Name>Nazwisko</Name>
                    <Type>varchar2(30)</Type>
                    <Description></Description>
                    <Nullable>false</Nullable>
                    <DefaultValue></DefaultValue>
                    <CheckExpression></CheckExpression>
                    <Properties/>
                </Column>
                <Column Id="c6">
                    <Name>Przydomek</Name>
                    <Type>varchar2(30)</Type>
                    <Description></Description>
                    <Nullable>false</Nullable>
                    <DefaultValue></DefaultValue>
                    <CheckExpression></CheckExpression>
                    <Properties/>
                </Column>
                <Column Id="c7">
                    <Name>Plec</Name>
                    <Type>char(1)</Type>
                    <Description></Description>
                    <Nullable>false</Nullable>
                    <DefaultValue></DefaultValue>
                    <CheckExpression></CheckExpression>
                    <Properties/>
                </Column>
                <Column Id="c3">
                    <Name>Wiek</Name>
                    <Type>integer</Type>
                    <Description></Description>
                    <Nullable>false</Nullable>
                    <DefaultValue></DefaultValue>
                    <CheckExpression></CheckExpression>
                    <Properties/>
                </Column>
                <Column Id="c4">
                    <Name>Wzrost</Name>
                    <Type>integer</Type>
                    <Description></Description>
                    <Nullable>false</Nullable>
                    <DefaultValue></DefaultValue>
                    <CheckExpression></CheckExpression>
                    <Properties/>
                </Column>
                <Column Id="c5">
                    <Name>Waga</Name>
                    <Type>integer</Type>
                    <Description></Description>
                    <Nullable>false</Nullable>
                    <DefaultValue></DefaultValue>
                    <CheckExpression></CheckExpression>
                    <Properties/>
                </Column>
                <Column Id="c56">
                    <Name>Dieta_ID</Name>
                    <Type>integer</Type>
                    <Description></Description>
                    <Nullable>false</Nullable>
                    <DefaultValue></DefaultValue>
                    <CheckExpression></CheckExpression>
                    <Properties/>
                </Column>
                <Column Id="c61">
                    <Name>Mieszkanie_ID</Name>
                    <Type>integer</Type>
                    <Description></Description>
                    <Nullable>false</Nullable>
                    <DefaultValue></DefaultValue>
                    <CheckExpression></CheckExpression>
                    <Properties/>
                </Column>
            </Columns>
            <PrimaryKey>
                <Name></Name>
                <Columns>
                    <Column>c1</Column>
                </Columns>
            </PrimaryKey>
            <AlternateKeys/>
            <Indexes/>
            <TableChecks>
                <TableCheck Id="tc1">
                    <Name>Plec</Name>
                    <Description></Description>
                    <CheckExpression>Plec IN ('M', 'F')</CheckExpression>
                    <Properties/>
                </TableCheck>
            </TableChecks>
            <AdditionalSQLBefore></AdditionalSQLBefore>
            <AdditionalSQLAfter></AdditionalSQLAfter>
            <Properties/>
        </Table>
        <Table Id="t3">
            <Name>Przywodca</Name>
            <Description></Description>
            <Columns>
                <Column Id="c30">
                    <Name>Osoba_ID</Name>
                    <Type>integer</Type>
                    <Description></Description>
                    <Nullable>false</Nullable>
                    <DefaultValue></DefaultValue>
                    <CheckExpression></CheckExpression>
                    <Properties/>
                </Column>
                <Column Id="c41">
                    <Name>Ranga</Name>
                    <Type>varchar2(30)</Type>
                    <Description></Description>
                    <Nullable>false</Nullable>
                    <DefaultValue></DefaultValue>
                    <CheckExpression></CheckExpression>
                    <Properties/>
                </Column>
                <Column Id="c32">
                    <Name>Pomocnik_ID</Name>
                    <Type>integer</Type>
                    <Description></Description>
                    <Nullable>true</Nullable>
                    <DefaultValue></DefaultValue>
                    <CheckExpression></CheckExpression>
                    <Properties/>
                </Column>
            </Columns>
            <PrimaryKey>
                <Name></Name>
                <Columns>
                    <Column>c30</Column>
                </Columns>
            </PrimaryKey>
            <AlternateKeys/>
            <Indexes/>
            <TableChecks/>
            <AdditionalSQLBefore></AdditionalSQLBefore>
            <AdditionalSQLAfter></AdditionalSQLAfter>
            <Properties/>
        </Table>
        <Table Id="t5">
            <Name>Mieszkanie</Name>
            <Description></Description>
            <Columns>
                <Column Id="c58">
                    <Name>ID</Name>
                    <Type>integer</Type>
                    <Description></Description>
                    <Nullable>false</Nullable>
                    <DefaultValue></DefaultValue>
                    <CheckExpression></CheckExpression>
                    <Properties/>
                </Column>
                <Column Id="c59">
                    <Name>Nazwa</Name>
                    <Type>varchar2(30)</Type>
                    <Description></Description>
                    <Nullable>false</Nullable>
                    <DefaultValue></DefaultValue>
                    <CheckExpression></CheckExpression>
                    <Properties/>
                </Column>
                <Column Id="c60">
                    <Name>Typ</Name>
                    <Type>varchar2(20)</Type>
                    <Description></Description>
                    <Nullable>false</Nullable>
                    <DefaultValue></DefaultValue>
                    <CheckExpression></CheckExpression>
                    <Properties/>
                </Column>
            </Columns>
            <PrimaryKey>
                <Name></Name>
                <Columns>
                    <Column>c58</Column>
                </Columns>
            </PrimaryKey>
            <AlternateKeys/>
            <Indexes/>
            <TableChecks/>
            <AdditionalSQLBefore></AdditionalSQLBefore>
            <AdditionalSQLAfter></AdditionalSQLAfter>
            <Properties/>
        </Table>
        <Table Id="t6">
            <Name>Bron</Name>
            <Description></Description>
            <Columns>
                <Column Id="c35">
                    <Name>ID</Name>
                    <Type>integer</Type>
                    <Description></Description>
                    <Nullable>false</Nullable>
                    <DefaultValue></DefaultValue>
                    <CheckExpression></CheckExpression>
                    <Properties/>
                </Column>
                <Column Id="c36">
                    <Name>Nazwa</Name>
                    <Type>varchar2(20)</Type>
                    <Description></Description>
                    <Nullable>false</Nullable>
                    <DefaultValue></DefaultValue>
                    <CheckExpression></CheckExpression>
                    <Properties/>
                </Column>
                <Column Id="c43">
                    <Name>Typ</Name>
                    <Type>varchar2(20)</Type>
                    <Description></Description>
                    <Nullable>false</Nullable>
                    <DefaultValue></DefaultValue>
                    <CheckExpression></CheckExpression>
                    <Properties/>
                </Column>
            </Columns>
            <PrimaryKey>
                <Name></Name>
                <Columns>
                    <Column>c35</Column>
                </Columns>
            </PrimaryKey>
            <AlternateKeys/>
            <Indexes/>
            <TableChecks/>
            <AdditionalSQLBefore></AdditionalSQLBefore>
            <AdditionalSQLAfter></AdditionalSQLAfter>
            <Properties/>
        </Table>
        <Table Id="t7">
            <Name>Dieta</Name>
            <Description></Description>
            <Columns>
                <Column Id="c24">
                    <Name>ID</Name>
                    <Type>integer</Type>
                    <Description></Description>
                    <Nullable>false</Nullable>
                    <DefaultValue></DefaultValue>
                    <CheckExpression></CheckExpression>
                    <Properties/>
                </Column>
                <Column Id="c45">
                    <Name>Nazwa</Name>
                    <Type>varchar2(20)</Type>
                    <Description></Description>
                    <Nullable>false</Nullable>
                    <DefaultValue></DefaultValue>
                    <CheckExpression></CheckExpression>
                    <Properties/>
                </Column>
                <Column Id="c46">
                    <Name>Typ</Name>
                    <Type>varchar2(20)</Type>
                    <Description></Description>
                    <Nullable>false</Nullable>
                    <DefaultValue></DefaultValue>
                    <CheckExpression></CheckExpression>
                    <Properties/>
                </Column>
            </Columns>
            <PrimaryKey>
                <Name></Name>
                <Columns>
                    <Column>c24</Column>
                </Columns>
            </PrimaryKey>
            <AlternateKeys/>
            <Indexes/>
            <TableChecks/>
            <AdditionalSQLBefore></AdditionalSQLBefore>
            <AdditionalSQLAfter></AdditionalSQLAfter>
            <Properties/>
        </Table>
        <Table Id="t8">
            <Name>Skladnik</Name>
            <Description></Description>
            <Columns>
                <Column Id="c14">
                    <Name>ID</Name>
                    <Type>integer</Type>
                    <Description></Description>
                    <Nullable>false</Nullable>
                    <DefaultValue></DefaultValue>
                    <CheckExpression></CheckExpression>
                    <Properties/>
                </Column>
                <Column Id="c23">
                    <Name>Nazwa</Name>
                    <Type>varchar2(40)</Type>
                    <Description></Description>
                    <Nullable>false</Nullable>
                    <DefaultValue></DefaultValue>
                    <CheckExpression></CheckExpression>
                    <Properties/>
                </Column>
            </Columns>
            <PrimaryKey>
                <Name></Name>
                <Columns>
                    <Column>c14</Column>
                </Columns>
            </PrimaryKey>
            <AlternateKeys/>
            <Indexes/>
            <TableChecks/>
            <AdditionalSQLBefore></AdditionalSQLBefore>
            <AdditionalSQLAfter></AdditionalSQLAfter>
            <Properties/>
        </Table>
        <Table Id="t9">
            <Name>Farmer</Name>
            <Description></Description>
            <Columns>
                <Column Id="c9">
                    <Name>Podwladny_ID</Name>
                    <Type>integer</Type>
                    <Description></Description>
                    <Nullable>false</Nullable>
                    <DefaultValue></DefaultValue>
                    <CheckExpression></CheckExpression>
                    <Properties/>
                </Column>
                <Column Id="c62">
                    <Name>Pomocnik_ID</Name>
                    <Type>integer</Type>
                    <Description></Description>
                    <Nullable>true</Nullable>
                    <DefaultValue></DefaultValue>
                    <CheckExpression></CheckExpression>
                    <Properties/>
                </Column>
            </Columns>
            <PrimaryKey>
                <Name></Name>
                <Columns>
                    <Column>c9</Column>
                </Columns>
            </PrimaryKey>
            <AlternateKeys/>
            <Indexes/>
            <TableChecks/>
            <AdditionalSQLBefore></AdditionalSQLBefore>
            <AdditionalSQLAfter></AdditionalSQLAfter>
            <Properties/>
        </Table>
        <Table Id="t10">
            <Name>Medyk</Name>
            <Description></Description>
            <Columns>
                <Column Id="c10">
                    <Name>Podwladny_ID</Name>
                    <Type>integer</Type>
                    <Description></Description>
                    <Nullable>false</Nullable>
                    <DefaultValue></DefaultValue>
                    <CheckExpression></CheckExpression>
                    <Properties/>
                </Column>
                <Column Id="c63">
                    <Name>Specjalizacja</Name>
                    <Type>varchar2(40)</Type>
                    <Description></Description>
                    <Nullable>false</Nullable>
                    <DefaultValue></DefaultValue>
                    <CheckExpression></CheckExpression>
                    <Properties/>
                </Column>
            </Columns>
            <PrimaryKey>
                <Name></Name>
                <Columns>
                    <Column>c10</Column>
                </Columns>
            </PrimaryKey>
            <AlternateKeys/>
            <Indexes/>
            <TableChecks/>
            <AdditionalSQLBefore></AdditionalSQLBefore>
            <AdditionalSQLAfter></AdditionalSQLAfter>
            <Properties/>
        </Table>
        <Table Id="t11">
            <Name>Wojownik</Name>
            <Description></Description>
            <Columns>
                <Column Id="c11">
                    <Name>Podwladny_ID</Name>
                    <Type>integer</Type>
                    <Description></Description>
                    <Nullable>false</Nullable>
                    <DefaultValue></DefaultValue>
                    <CheckExpression></CheckExpression>
                    <Properties/>
                </Column>
                <Column Id="c65">
                    <Name>Doswiadczenie</Name>
                    <Type>integer</Type>
                    <Description></Description>
                    <Nullable>false</Nullable>
                    <DefaultValue></DefaultValue>
                    <CheckExpression></CheckExpression>
                    <Properties/>
                </Column>
            </Columns>
            <PrimaryKey>
                <Name></Name>
                <Columns>
                    <Column>c11</Column>
                </Columns>
            </PrimaryKey>
            <AlternateKeys/>
            <Indexes/>
            <TableChecks/>
            <AdditionalSQLBefore></AdditionalSQLBefore>
            <AdditionalSQLAfter></AdditionalSQLAfter>
            <Properties/>
        </Table>
        <Table Id="t13">
            <Name>Farmer_Skladnik</Name>
            <Description></Description>
            <Columns>
                <Column Id="c15">
                    <Name>Farmer_ID</Name>
                    <Type>integer</Type>
                    <Description></Description>
                    <Nullable>false</Nullable>
                    <DefaultValue></DefaultValue>
                    <CheckExpression></CheckExpression>
                    <Properties/>
                </Column>
                <Column Id="c16">
                    <Name>Skladnik_ID</Name>
                    <Type>integer</Type>
                    <Description></Description>
                    <Nullable>false</Nullable>
                    <DefaultValue></DefaultValue>
                    <CheckExpression></CheckExpression>
                    <Properties/>
                </Column>
                <Column Id="c17">
                    <Name>Produkcja</Name>
                    <Type>integer</Type>
                    <Description></Description>
                    <Nullable>false</Nullable>
                    <DefaultValue></DefaultValue>
                    <CheckExpression></CheckExpression>
                    <Properties/>
                </Column>
            </Columns>
            <PrimaryKey>
                <Name></Name>
                <Columns>
                    <Column>c16</Column>
                    <Column>c15</Column>
                </Columns>
            </PrimaryKey>
            <AlternateKeys/>
            <Indexes/>
            <TableChecks/>
            <AdditionalSQLBefore></AdditionalSQLBefore>
            <AdditionalSQLAfter></AdditionalSQLAfter>
            <Properties/>
        </Table>
        <Table Id="t15">
            <Name>Skladnik_Dieta</Name>
            <Description></Description>
            <Columns>
                <Column Id="c26">
                    <Name>Dieta_ID</Name>
                    <Type>integer</Type>
                    <Description></Description>
                    <Nullable>false</Nullable>
                    <DefaultValue></DefaultValue>
                    <CheckExpression></CheckExpression>
                    <Properties/>
                </Column>
                <Column Id="c25">
                    <Name>Skladnik_ID</Name>
                    <Type>integer</Type>
                    <Description></Description>
                    <Nullable>false</Nullable>
                    <DefaultValue></DefaultValue>
                    <CheckExpression></CheckExpression>
                    <Properties/>
                </Column>
                <Column Id="c27">
                    <Name>Ilosc</Name>
                    <Type>integer</Type>
                    <Description></Description>
                    <Nullable>false</Nullable>
                    <DefaultValue></DefaultValue>
                    <CheckExpression></CheckExpression>
                    <Properties/>
                </Column>
            </Columns>
            <PrimaryKey>
                <Name></Name>
                <Columns>
                    <Column>c25</Column>
                    <Column>c26</Column>
                </Columns>
            </PrimaryKey>
            <AlternateKeys/>
            <Indexes/>
            <TableChecks/>
            <AdditionalSQLBefore></AdditionalSQLBefore>
            <AdditionalSQLAfter></AdditionalSQLAfter>
            <Properties/>
        </Table>
        <Table Id="t17">
            <Name>Przywodca_Podwladny</Name>
            <Description></Description>
            <Columns>
                <Column Id="c39">
                    <Name>Przywodca_ID</Name>
                    <Type>integer</Type>
                    <Description></Description>
                    <Nullable>false</Nullable>
                    <DefaultValue></DefaultValue>
                    <CheckExpression></CheckExpression>
                    <Properties/>
                </Column>
                <Column Id="c40">
                    <Name>Podwladny_ID</Name>
                    <Type>integer</Type>
                    <Description></Description>
                    <Nullable>false</Nullable>
                    <DefaultValue></DefaultValue>
                    <CheckExpression></CheckExpression>
                    <Properties/>
                </Column>
            </Columns>
            <PrimaryKey>
                <Name></Name>
                <Columns>
                    <Column>c39</Column>
                    <Column>c40</Column>
                </Columns>
            </PrimaryKey>
            <AlternateKeys/>
            <Indexes/>
            <TableChecks/>
            <AdditionalSQLBefore></AdditionalSQLBefore>
            <AdditionalSQLAfter></AdditionalSQLAfter>
            <Properties/>
        </Table>
        <Table Id="t18">
            <Name>Wojownik_Bron</Name>
            <Description></Description>
            <Columns>
                <Column Id="c34">
                    <Name>Wojownik_ID</Name>
                    <Type>integer</Type>
                    <Description></Description>
                    <Nullable>false</Nullable>
                    <DefaultValue></DefaultValue>
                    <CheckExpression></CheckExpression>
                    <Properties/>
                </Column>
                <Column Id="c38">
                    <Name>Bron_ID</Name>
                    <Type>integer</Type>
                    <Description></Description>
                    <Nullable>false</Nullable>
                    <DefaultValue></DefaultValue>
                    <CheckExpression></CheckExpression>
                    <Properties/>
                </Column>
            </Columns>
            <PrimaryKey>
                <Name></Name>
                <Columns>
                    <Column>c38</Column>
                    <Column>c34</Column>
                </Columns>
            </PrimaryKey>
            <AlternateKeys/>
            <Indexes/>
            <TableChecks/>
            <AdditionalSQLBefore></AdditionalSQLBefore>
            <AdditionalSQLAfter></AdditionalSQLAfter>
            <Properties/>
        </Table>
        <Table Id="t20">
            <Name>Leczenie</Name>
            <Description></Description>
            <Columns>
                <Column Id="c64">
                    <Name>ID</Name>
                    <Type>integer</Type>
                    <Description></Description>
                    <Nullable>false</Nullable>
                    <DefaultValue></DefaultValue>
                    <CheckExpression></CheckExpression>
                    <Properties/>
                </Column>
                <Column Id="c53">
                    <Name>Osoba_ID</Name>
                    <Type>integer</Type>
                    <Description></Description>
                    <Nullable>false</Nullable>
                    <DefaultValue></DefaultValue>
                    <CheckExpression></CheckExpression>
                    <Properties/>
                </Column>
                <Column Id="c54">
                    <Name>Medyk_ID</Name>
                    <Type>integer</Type>
                    <Description></Description>
                    <Nullable>false</Nullable>
                    <DefaultValue></DefaultValue>
                    <CheckExpression></CheckExpression>
                    <Properties/>
                </Column>
                <Column Id="c57">
                    <Name>Choroba</Name>
                    <Type>varchar2(40)</Type>
                    <Description></Description>
                    <Nullable>false</Nullable>
                    <DefaultValue></DefaultValue>
                    <CheckExpression></CheckExpression>
                    <Properties/>
                </Column>
            </Columns>
            <PrimaryKey>
                <Name></Name>
                <Columns>
                    <Column>c64</Column>
                </Columns>
            </PrimaryKey>
            <AlternateKeys/>
            <Indexes/>
            <TableChecks/>
            <AdditionalSQLBefore></AdditionalSQLBefore>
            <AdditionalSQLAfter></AdditionalSQLAfter>
            <Properties/>
        </Table>
    </Tables>
    <ExternalTables/>
    <Views/>
    <MaterializedViews/>
    <References>
        <Reference Id="r1">
            <Name>Osoba_Podwladny</Name>
            <Description></Description>
            <PKTable>t2</PKTable>
            <FKTable>t1</FKTable>
            <PKRole></PKRole>
            <FKRole></FKRole>
            <ReferenceColumns>
                <ReferenceColumn>
                    <PKColumn>c1</PKColumn>
                    <FKColumn>c8</FKColumn>
                </ReferenceColumn>
            </ReferenceColumns>
            <Cardinality>0..1</Cardinality>
            <Mandatory>true</Mandatory>
            <OnUpdateAction>None</OnUpdateAction>
            <OnDeleteAction>None</OnDeleteAction>
            <Properties/>
        </Reference>
        <Reference Id="r2">
            <Name>Podwladny_Farmer</Name>
            <Description></Description>
            <PKTable>t1</PKTable>
            <FKTable>t9</FKTable>
            <PKRole></PKRole>
            <FKRole></FKRole>
            <ReferenceColumns>
                <ReferenceColumn>
                    <PKColumn>c8</PKColumn>
                    <FKColumn>c9</FKColumn>
                </ReferenceColumn>
            </ReferenceColumns>
            <Cardinality>0..1</Cardinality>
            <Mandatory>true</Mandatory>
            <OnUpdateAction>None</OnUpdateAction>
            <OnDeleteAction>None</OnDeleteAction>
            <Properties/>
        </Reference>
        <Reference Id="r3">
            <Name>Podwladny_Medyk</Name>
            <Description></Description>
            <PKTable>t1</PKTable>
            <FKTable>t10</FKTable>
            <PKRole></PKRole>
            <FKRole></FKRole>
            <ReferenceColumns>
                <ReferenceColumn>
                    <PKColumn>c8</PKColumn>
                    <FKColumn>c10</FKColumn>
                </ReferenceColumn>
            </ReferenceColumns>
            <Cardinality>0..1</Cardinality>
            <Mandatory>true</Mandatory>
            <OnUpdateAction>None</OnUpdateAction>
            <OnDeleteAction>None</OnDeleteAction>
            <Properties/>
        </Reference>
        <Reference Id="r4">
            <Name>Podwladny_Wojownik</Name>
            <Description></Description>
            <PKTable>t1</PKTable>
            <FKTable>t11</FKTable>
            <PKRole></PKRole>
            <FKRole></FKRole>
            <ReferenceColumns>
                <ReferenceColumn>
                    <PKColumn>c8</PKColumn>
                    <FKColumn>c11</FKColumn>
                </ReferenceColumn>
            </ReferenceColumns>
            <Cardinality>0..1</Cardinality>
            <Mandatory>true</Mandatory>
            <OnUpdateAction>None</OnUpdateAction>
            <OnDeleteAction>None</OnDeleteAction>
            <Properties/>
        </Reference>
        <Reference Id="r7">
            <Name>Farmer_Skladnik</Name>
            <Description></Description>
            <PKTable>t9</PKTable>
            <FKTable>t13</FKTable>
            <PKRole></PKRole>
            <FKRole></FKRole>
            <ReferenceColumns>
                <ReferenceColumn>
                    <PKColumn>c9</PKColumn>
                    <FKColumn>c15</FKColumn>
                </ReferenceColumn>
            </ReferenceColumns>
            <Cardinality>0..*</Cardinality>
            <Mandatory>true</Mandatory>
            <OnUpdateAction>None</OnUpdateAction>
            <OnDeleteAction>None</OnDeleteAction>
            <Properties/>
        </Reference>
        <Reference Id="r8">
            <Name>Skladnik_Farmer</Name>
            <Description></Description>
            <PKTable>t8</PKTable>
            <FKTable>t13</FKTable>
            <PKRole></PKRole>
            <FKRole></FKRole>
            <ReferenceColumns>
                <ReferenceColumn>
                    <PKColumn>c14</PKColumn>
                    <FKColumn>c16</FKColumn>
                </ReferenceColumn>
            </ReferenceColumns>
            <Cardinality>0..*</Cardinality>
            <Mandatory>true</Mandatory>
            <OnUpdateAction>None</OnUpdateAction>
            <OnDeleteAction>None</OnDeleteAction>
            <Properties/>
        </Reference>
        <Reference Id="r10">
            <Name>Skladnik_Dieta</Name>
            <Description></Description>
            <PKTable>t8</PKTable>
            <FKTable>t15</FKTable>
            <PKRole></PKRole>
            <FKRole></FKRole>
            <ReferenceColumns>
                <ReferenceColumn>
                    <PKColumn>c14</PKColumn>
                    <FKColumn>c25</FKColumn>
                </ReferenceColumn>
            </ReferenceColumns>
            <Cardinality>0..*</Cardinality>
            <Mandatory>true</Mandatory>
            <OnUpdateAction>None</OnUpdateAction>
            <OnDeleteAction>None</OnDeleteAction>
            <Properties/>
        </Reference>
        <Reference Id="r11">
            <Name>Dieta_Skladnik</Name>
            <Description></Description>
            <PKTable>t7</PKTable>
            <FKTable>t15</FKTable>
            <PKRole></PKRole>
            <FKRole></FKRole>
            <ReferenceColumns>
                <ReferenceColumn>
                    <PKColumn>c24</PKColumn>
                    <FKColumn>c26</FKColumn>
                </ReferenceColumn>
            </ReferenceColumns>
            <Cardinality>0..*</Cardinality>
            <Mandatory>true</Mandatory>
            <OnUpdateAction>None</OnUpdateAction>
            <OnDeleteAction>None</OnDeleteAction>
            <Properties/>
        </Reference>
        <Reference Id="r14">
            <Name>Osoba_Przywodca</Name>
            <Description></Description>
            <PKTable>t2</PKTable>
            <FKTable>t3</FKTable>
            <PKRole></PKRole>
            <FKRole></FKRole>
            <ReferenceColumns>
                <ReferenceColumn>
                    <PKColumn>c1</PKColumn>
                    <FKColumn>c30</FKColumn>
                </ReferenceColumn>
            </ReferenceColumns>
            <Cardinality>0..1</Cardinality>
            <Mandatory>true</Mandatory>
            <OnUpdateAction>None</OnUpdateAction>
            <OnDeleteAction>None</OnDeleteAction>
            <Properties/>
        </Reference>
        <Reference Id="r17">
            <Name>Przywodca_Przywodca</Name>
            <Description></Description>
            <PKTable>t3</PKTable>
            <FKTable>t3</FKTable>
            <PKRole></PKRole>
            <FKRole></FKRole>
            <ReferenceColumns>
                <ReferenceColumn>
                    <PKColumn>c30</PKColumn>
                    <FKColumn>c32</FKColumn>
                </ReferenceColumn>
            </ReferenceColumns>
            <Cardinality>0..*</Cardinality>
            <Mandatory>false</Mandatory>
            <OnUpdateAction>None</OnUpdateAction>
            <OnDeleteAction>None</OnDeleteAction>
            <Properties/>
        </Reference>
        <Reference Id="r18">
            <Name>Wojownik_Bron</Name>
            <Description></Description>
            <PKTable>t11</PKTable>
            <FKTable>t18</FKTable>
            <PKRole></PKRole>
            <FKRole></FKRole>
            <ReferenceColumns>
                <ReferenceColumn>
                    <PKColumn>c11</PKColumn>
                    <FKColumn>c34</FKColumn>
                </ReferenceColumn>
            </ReferenceColumns>
            <Cardinality>0..*</Cardinality>
            <Mandatory>true</Mandatory>
            <OnUpdateAction>None</OnUpdateAction>
            <OnDeleteAction>None</OnDeleteAction>
            <Properties/>
        </Reference>
        <Reference Id="r19">
            <Name>Bron_Wojownik</Name>
            <Description></Description>
            <PKTable>t6</PKTable>
            <FKTable>t18</FKTable>
            <PKRole></PKRole>
            <FKRole></FKRole>
            <ReferenceColumns>
                <ReferenceColumn>
                    <PKColumn>c35</PKColumn>
                    <FKColumn>c38</FKColumn>
                </ReferenceColumn>
            </ReferenceColumns>
            <Cardinality>0..*</Cardinality>
            <Mandatory>true</Mandatory>
            <OnUpdateAction>None</OnUpdateAction>
            <OnDeleteAction>None</OnDeleteAction>
            <Properties/>
        </Reference>
        <Reference Id="r20">
            <Name>Przywodca_Podwladny_Przywodca</Name>
            <Description></Description>
            <PKTable>t3</PKTable>
            <FKTable>t17</FKTable>
            <PKRole></PKRole>
            <FKRole></FKRole>
            <ReferenceColumns>
                <ReferenceColumn>
                    <PKColumn>c30</PKColumn>
                    <FKColumn>c39</FKColumn>
                </ReferenceColumn>
            </ReferenceColumns>
            <Cardinality>0..*</Cardinality>
            <Mandatory>true</Mandatory>
            <OnUpdateAction>None</OnUpdateAction>
            <OnDeleteAction>None</OnDeleteAction>
            <Properties/>
        </Reference>
        <Reference Id="r21">
            <Name>Przywodca_Przywodca_Podwladny</Name>
            <Description></Description>
            <PKTable>t1</PKTable>
            <FKTable>t17</FKTable>
            <PKRole></PKRole>
            <FKRole></FKRole>
            <ReferenceColumns>
                <ReferenceColumn>
                    <PKColumn>c8</PKColumn>
                    <FKColumn>c40</FKColumn>
                </ReferenceColumn>
            </ReferenceColumns>
            <Cardinality>0..*</Cardinality>
            <Mandatory>true</Mandatory>
            <OnUpdateAction>None</OnUpdateAction>
            <OnDeleteAction>None</OnDeleteAction>
            <Properties/>
        </Reference>
        <Reference Id="r23">
            <Name>Osoba_Leczenie</Name>
            <Description></Description>
            <PKTable>t2</PKTable>
            <FKTable>t20</FKTable>
            <PKRole></PKRole>
            <FKRole></FKRole>
            <ReferenceColumns>
                <ReferenceColumn>
                    <PKColumn>c1</PKColumn>
                    <FKColumn>c53</FKColumn>
                </ReferenceColumn>
            </ReferenceColumns>
            <Cardinality>0..*</Cardinality>
            <Mandatory>true</Mandatory>
            <OnUpdateAction>None</OnUpdateAction>
            <OnDeleteAction>None</OnDeleteAction>
            <Properties/>
        </Reference>
        <Reference Id="r24">
            <Name>Medyk_Leczenie</Name>
            <Description></Description>
            <PKTable>t10</PKTable>
            <FKTable>t20</FKTable>
            <PKRole></PKRole>
            <FKRole></FKRole>
            <ReferenceColumns>
                <ReferenceColumn>
                    <PKColumn>c10</PKColumn>
                    <FKColumn>c54</FKColumn>
                </ReferenceColumn>
            </ReferenceColumns>
            <Cardinality>0..*</Cardinality>
            <Mandatory>true</Mandatory>
            <OnUpdateAction>None</OnUpdateAction>
            <OnDeleteAction>None</OnDeleteAction>
            <Properties/>
        </Reference>
        <Reference Id="r25">
            <Name>Osoba_Dieta</Name>
            <Description></Description>
            <PKTable>t7</PKTable>
            <FKTable>t2</FKTable>
            <PKRole></PKRole>
            <FKRole></FKRole>
            <ReferenceColumns>
                <ReferenceColumn>
                    <PKColumn>c24</PKColumn>
                    <FKColumn>c56</FKColumn>
                </ReferenceColumn>
            </ReferenceColumns>
            <Cardinality>0..*</Cardinality>
            <Mandatory>true</Mandatory>
            <OnUpdateAction>None</OnUpdateAction>
            <OnDeleteAction>None</OnDeleteAction>
            <Properties/>
        </Reference>
        <Reference Id="r26">
            <Name>Osoba_Mieszkanie</Name>
            <Description></Description>
            <PKTable>t5</PKTable>
            <FKTable>t2</FKTable>
            <PKRole></PKRole>
            <FKRole></FKRole>
            <ReferenceColumns>
                <ReferenceColumn>
                    <PKColumn>c58</PKColumn>
                    <FKColumn>c61</FKColumn>
                </ReferenceColumn>
            </ReferenceColumns>
            <Cardinality>1..*</Cardinality>
            <Mandatory>true</Mandatory>
            <OnUpdateAction>None</OnUpdateAction>
            <OnDeleteAction>None</OnDeleteAction>
            <Properties/>
        </Reference>
        <Reference Id="r27">
            <Name>Farmer_Farmer</Name>
            <Description></Description>
            <PKTable>t9</PKTable>
            <FKTable>t9</FKTable>
            <PKRole></PKRole>
            <FKRole></FKRole>
            <ReferenceColumns>
                <ReferenceColumn>
                    <PKColumn>c9</PKColumn>
                    <FKColumn>c62</FKColumn>
                </ReferenceColumn>
            </ReferenceColumns>
            <Cardinality>0..*</Cardinality>
            <Mandatory>false</Mandatory>
            <OnUpdateAction>None</OnUpdateAction>
            <OnDeleteAction>None</OnDeleteAction>
            <Properties/>
        </Reference>
    </References>
    <Sequences/>
    <Notes>
        <Note Id="n1">
            <Name>Sex_note</Name>
            <Content>Plec:
M - mężczyzna
F - kobieta</Content>
            <DisplayInfo>
                <X>6715.5</X>
                <Y>6711.5</Y>
                <Width>98.0</Width>
                <Height>58.0</Height>
                <LineColor>#000000</LineColor>
                <FillColor>#fff9c3</FillColor>
            </DisplayInfo>
        </Note>
        <Note Id="n2">
            <Name>Author</Name>
            <Content>"Miasto Teotihuacán"
Maciej Sepeta
s30518 19c</Content>
            <DisplayInfo>
                <X>6356.5</X>
                <Y>6556.5</Y>
                <Width>154.0</Width>
                <Height>58.0</Height>
                <LineColor>#00FF00</LineColor>
                <FillColor>#fff9c3</FillColor>
            </DisplayInfo>
        </Note>
    </Notes>
    <Areas/>
    <Texts/>
    <TableDisplays>
        <TableDisplay Id="td1">
            <X>6860.5</X>
            <Y>6883.5</Y>
            <Width>159.0</Width>
            <Height>61.0</Height>
            <LineColor>#000000</LineColor>
            <FillColor>#ffffff</FillColor>
            <Table>t1</Table>
            <FixedSize>false</FixedSize>
        </TableDisplay>
        <TableDisplay Id="td2">
            <X>6844.5</X>
            <Y>6682.5</Y>
            <Width>203.0</Width>
            <Height>174.0</Height>
            <LineColor>#000000</LineColor>
            <FillColor>#ffffff</FillColor>
            <Table>t2</Table>
            <FixedSize>false</FixedSize>
        </TableDisplay>
        <TableDisplay Id="td3">
            <X>7101.5</X>
            <Y>6908.5</Y>
            <Width>239.0</Width>
            <Height>82.0</Height>
            <LineColor>#000000</LineColor>
            <FillColor>#ffffff</FillColor>
            <Table>t3</Table>
            <FixedSize>false</FixedSize>
        </TableDisplay>
        <TableDisplay Id="td5">
            <X>7091.5</X>
            <Y>6545.5</Y>
            <Width>150.0</Width>
            <Height>73.0</Height>
            <LineColor>#000000</LineColor>
            <FillColor>#ffffff</FillColor>
            <Table>t5</Table>
            <FixedSize>false</FixedSize>
        </TableDisplay>
        <TableDisplay Id="td6">
            <X>6955.5</X>
            <Y>7011.5</Y>
            <Width>176.0</Width>
            <Height>73.0</Height>
            <LineColor>#000000</LineColor>
            <FillColor>#ffffff</FillColor>
            <Table>t6</Table>
            <FixedSize>false</FixedSize>
        </TableDisplay>
        <TableDisplay Id="td7">
            <X>7302.5</X>
            <Y>7240.5</Y>
            <Width>156.0</Width>
            <Height>73.0</Height>
            <LineColor>#000000</LineColor>
            <FillColor>#ffffff</FillColor>
            <Table>t7</Table>
            <FixedSize>false</FixedSize>
        </TableDisplay>
        <TableDisplay Id="td8">
            <X>6454.5</X>
            <Y>7233.5</Y>
            <Width>166.0</Width>
            <Height>58.0</Height>
            <LineColor>#000000</LineColor>
            <FillColor>#ffffff</FillColor>
            <Table>t8</Table>
            <FixedSize>false</FixedSize>
        </TableDisplay>
        <TableDisplay Id="td9">
            <X>6387.5</X>
            <Y>6954.5</Y>
            <Width>201.0</Width>
            <Height>60.0</Height>
            <LineColor>#000000</LineColor>
            <FillColor>#ffffff</FillColor>
            <Table>t9</Table>
            <FixedSize>false</FixedSize>
        </TableDisplay>
        <TableDisplay Id="td10">
            <X>6442.5</X>
            <Y>6710.5</Y>
            <Width>237.0</Width>
            <Height>61.0</Height>
            <LineColor>#000000</LineColor>
            <FillColor>#ffffff</FillColor>
            <Table>t10</Table>
            <FixedSize>false</FixedSize>
        </TableDisplay>
        <TableDisplay Id="td11">
            <X>6813.5</X>
            <Y>7112.5</Y>
            <Width>226.0</Width>
            <Height>60.0</Height>
            <LineColor>#000000</LineColor>
            <FillColor>#ffffff</FillColor>
            <Table>t11</Table>
            <FixedSize>false</FixedSize>
        </TableDisplay>
        <TableDisplay Id="td13">
            <X>6386.5</X>
            <Y>7064.5</Y>
            <Width>219.0</Width>
            <Height>73.0</Height>
            <LineColor>#000000</LineColor>
            <FillColor>#ffffff</FillColor>
            <Table>t13</Table>
            <FixedSize>false</FixedSize>
        </TableDisplay>
        <TableDisplay Id="td15">
            <X>6855.5</X>
            <Y>7241.5</Y>
            <Width>185.0</Width>
            <Height>73.0</Height>
            <LineColor>#000000</LineColor>
            <FillColor>#ffffff</FillColor>
            <Table>t15</Table>
            <FixedSize>false</FixedSize>
        </TableDisplay>
        <TableDisplay Id="td17">
            <X>7145.5</X>
            <Y>6779.5</Y>
            <Width>192.0</Width>
            <Height>61.0</Height>
            <LineColor>#000000</LineColor>
            <FillColor>#ffffff</FillColor>
            <Table>t17</Table>
            <FixedSize>false</FixedSize>
        </TableDisplay>
        <TableDisplay Id="td18">
            <X>7136.5</X>
            <Y>7129.5</Y>
            <Width>227.0</Width>
            <Height>60.0</Height>
            <LineColor>#000000</LineColor>
            <FillColor>#ffffff</FillColor>
            <Table>t18</Table>
            <FixedSize>false</FixedSize>
        </TableDisplay>
        <TableDisplay Id="td20">
            <X>6694.5</X>
            <Y>6545.5</Y>
            <Width>257.0</Width>
            <Height>87.0</Height>
            <LineColor>#000000</LineColor>
            <FillColor>#ffffff</FillColor>
            <Table>t20</Table>
            <FixedSize>false</FixedSize>
        </TableDisplay>
    </TableDisplays>
    <ExternalTableDisplays/>
    <ViewDisplays/>
    <MaterializedViewDisplays/>
    <ReferenceDisplays>
        <ReferenceDisplay Id="rd1">
            <Color>#000000</Color>
            <Type>Vertical_2CP</Type>
            <ControlPoints>
                <ControlPoint>
                    <X>6959.5</X>
                    <Y>6741.5</Y>
                </ControlPoint>
                <ControlPoint>
                    <X>6959.5</X>
                    <Y>6912.5</Y>
                </ControlPoint>
            </ControlPoints>
            <PkTableDisplay>td2</PkTableDisplay>
            <FkTableDisplay>td1</FkTableDisplay>
            <Reference>r1</Reference>
        </ReferenceDisplay>
        <ReferenceDisplay Id="rd2">
            <Color>#000000</Color>
            <Type>Horizontal_4CP</Type>
            <ControlPoints>
                <ControlPoint>
                    <X>6935.5</X>
                    <Y>6926.5</Y>
                </ControlPoint>
                <ControlPoint>
                    <X>6507.5</X>
                    <Y>6926.5</Y>
                </ControlPoint>
                <ControlPoint>
                    <X>6507.5</X>
                    <Y>6964.5</Y>
                </ControlPoint>
                <ControlPoint>
                    <X>6427.5</X>
                    <Y>6964.5</Y>
                </ControlPoint>
            </ControlPoints>
            <PkTableDisplay>td1</PkTableDisplay>
            <FkTableDisplay>td9</FkTableDisplay>
            <Reference>r2</Reference>
        </ReferenceDisplay>
        <ReferenceDisplay Id="rd3">
            <Color>#000000</Color>
            <Type>Cross_3CP</Type>
            <ControlPoints>
                <ControlPoint>
                    <X>6936.5</X>
                    <Y>6897.5</Y>
                </ControlPoint>
                <ControlPoint>
                    <X>6523.5</X>
                    <Y>6897.5</Y>
                </ControlPoint>
                <ControlPoint>
                    <X>6523.5</X>
                    <Y>6747.5</Y>
                </ControlPoint>
            </ControlPoints>
            <PkTableDisplay>td1</PkTableDisplay>
            <FkTableDisplay>td10</FkTableDisplay>
            <Reference>r3</Reference>
        </ReferenceDisplay>
        <ReferenceDisplay Id="rd4">
            <Color>#000000</Color>
            <Type>Vertical_4CP</Type>
            <ControlPoints>
                <ControlPoint>
                    <X>6870.5</X>
                    <Y>6911.5</Y>
                </ControlPoint>
                <ControlPoint>
                    <X>6870.5</X>
                    <Y>7063.5</Y>
                </ControlPoint>
                <ControlPoint>
                    <X>6823.5</X>
                    <Y>7063.5</Y>
                </ControlPoint>
                <ControlPoint>
                    <X>6823.5</X>
                    <Y>7147.5</Y>
                </ControlPoint>
            </ControlPoints>
            <PkTableDisplay>td1</PkTableDisplay>
            <FkTableDisplay>td11</FkTableDisplay>
            <Reference>r4</Reference>
        </ReferenceDisplay>
        <ReferenceDisplay Id="rd7">
            <Color>#000000</Color>
            <Type>Vertical_2CP</Type>
            <ControlPoints>
                <ControlPoint>
                    <X>6493.5</X>
                    <Y>6993.5</Y>
                </ControlPoint>
                <ControlPoint>
                    <X>6493.5</X>
                    <Y>7094.5</Y>
                </ControlPoint>
            </ControlPoints>
            <PkTableDisplay>td9</PkTableDisplay>
            <FkTableDisplay>td13</FkTableDisplay>
            <Reference>r7</Reference>
        </ReferenceDisplay>
        <ReferenceDisplay Id="rd8">
            <Color>#000000</Color>
            <Type>Horizontal_4CP</Type>
            <ControlPoints>
                <ControlPoint>
                    <X>6513.5</X>
                    <Y>7243.5</Y>
                </ControlPoint>
                <ControlPoint>
                    <X>6486.5</X>
                    <Y>7243.5</Y>
                </ControlPoint>
                <ControlPoint>
                    <X>6486.5</X>
                    <Y>7110.5</Y>
                </ControlPoint>
                <ControlPoint>
                    <X>6467.5</X>
                    <Y>7110.5</Y>
                </ControlPoint>
            </ControlPoints>
            <PkTableDisplay>td8</PkTableDisplay>
            <FkTableDisplay>td13</FkTableDisplay>
            <Reference>r8</Reference>
        </ReferenceDisplay>
        <ReferenceDisplay Id="rd10">
            <Color>#000000</Color>
            <Type>Horizontal_4CP</Type>
            <ControlPoints>
                <ControlPoint>
                    <X>6526.5</X>
                    <Y>7281.5</Y>
                </ControlPoint>
                <ControlPoint>
                    <X>6681.5</X>
                    <Y>7281.5</Y>
                </ControlPoint>
                <ControlPoint>
                    <X>6681.5</X>
                    <Y>7288.5</Y>
                </ControlPoint>
                <ControlPoint>
                    <X>6919.5</X>
                    <Y>7288.5</Y>
                </ControlPoint>
            </ControlPoints>
            <PkTableDisplay>td8</PkTableDisplay>
            <FkTableDisplay>td15</FkTableDisplay>
            <Reference>r10</Reference>
        </ReferenceDisplay>
        <ReferenceDisplay Id="rd11">
            <Color>#000000</Color>
            <Type>Horizontal_4CP</Type>
            <ControlPoints>
                <ControlPoint>
                    <X>7385.5</X>
                    <Y>7290.5</Y>
                </ControlPoint>
                <ControlPoint>
                    <X>7107.5</X>
                    <Y>7290.5</Y>
                </ControlPoint>
                <ControlPoint>
                    <X>7107.5</X>
                    <Y>7289.5</Y>
                </ControlPoint>
                <ControlPoint>
                    <X>6948.5</X>
                    <Y>7289.5</Y>
                </ControlPoint>
            </ControlPoints>
            <PkTableDisplay>td7</PkTableDisplay>
            <FkTableDisplay>td15</FkTableDisplay>
            <Reference>r11</Reference>
        </ReferenceDisplay>
        <ReferenceDisplay Id="rd14">
            <Color>#000000</Color>
            <Type>Horizontal_4CP</Type>
            <ControlPoints>
                <ControlPoint>
                    <X>6932.5</X>
                    <Y>6728.5</Y>
                </ControlPoint>
                <ControlPoint>
                    <X>7398.5</X>
                    <Y>6728.5</Y>
                </ControlPoint>
                <ControlPoint>
                    <X>7398.5</X>
                    <Y>6918.5</Y>
                </ControlPoint>
                <ControlPoint>
                    <X>7157.5</X>
                    <Y>6918.5</Y>
                </ControlPoint>
            </ControlPoints>
            <PkTableDisplay>td2</PkTableDisplay>
            <FkTableDisplay>td3</FkTableDisplay>
            <Reference>r14</Reference>
        </ReferenceDisplay>
        <ReferenceDisplay Id="rd17">
            <Color>#000000</Color>
            <Type>Self_5CP</Type>
            <ControlPoints>
                <ControlPoint>
                    <X>7225.5</X>
                    <Y>6938.5</Y>
                </ControlPoint>
                <ControlPoint>
                    <X>7225.5</X>
                    <Y>7008.5</Y>
                </ControlPoint>
                <ControlPoint>
                    <X>7360.5</X>
                    <Y>7008.5</Y>
                </ControlPoint>
                <ControlPoint>
                    <X>7360.5</X>
                    <Y>6936.5</Y>
                </ControlPoint>
                <ControlPoint>
                    <X>7284.5</X>
                    <Y>6936.5</Y>
                </ControlPoint>
            </ControlPoints>
            <PkTableDisplay>td3</PkTableDisplay>
            <FkTableDisplay>td3</FkTableDisplay>
            <Reference>r17</Reference>
        </ReferenceDisplay>
        <ReferenceDisplay Id="rd18">
            <Color>#000000</Color>
            <Type>Vertical_4CP</Type>
            <ControlPoints>
                <ControlPoint>
                    <X>6992.5</X>
                    <Y>7156.5</Y>
                </ControlPoint>
                <ControlPoint>
                    <X>6992.5</X>
                    <Y>7151.5</Y>
                </ControlPoint>
                <ControlPoint>
                    <X>7193.5</X>
                    <Y>7151.5</Y>
                </ControlPoint>
                <ControlPoint>
                    <X>7193.5</X>
                    <Y>7159.5</Y>
                </ControlPoint>
            </ControlPoints>
            <PkTableDisplay>td11</PkTableDisplay>
            <FkTableDisplay>td18</FkTableDisplay>
            <Reference>r18</Reference>
        </ReferenceDisplay>
        <ReferenceDisplay Id="rd19">
            <Color>#000000</Color>
            <Type>Vertical_4CP</Type>
            <ControlPoints>
                <ControlPoint>
                    <X>7090.5</X>
                    <Y>7040.5</Y>
                </ControlPoint>
                <ControlPoint>
                    <X>7090.5</X>
                    <Y>7057.5</Y>
                </ControlPoint>
                <ControlPoint>
                    <X>7192.5</X>
                    <Y>7057.5</Y>
                </ControlPoint>
                <ControlPoint>
                    <X>7192.5</X>
                    <Y>7162.5</Y>
                </ControlPoint>
            </ControlPoints>
            <PkTableDisplay>td6</PkTableDisplay>
            <FkTableDisplay>td18</FkTableDisplay>
            <Reference>r19</Reference>
        </ReferenceDisplay>
        <ReferenceDisplay Id="rd20">
            <Color>#000000</Color>
            <Type>Horizontal_4CP</Type>
            <ControlPoints>
                <ControlPoint>
                    <X>7184.5</X>
                    <Y>6918.5</Y>
                </ControlPoint>
                <ControlPoint>
                    <X>7211.5</X>
                    <Y>6918.5</Y>
                </ControlPoint>
                <ControlPoint>
                    <X>7211.5</X>
                    <Y>6811.5</Y>
                </ControlPoint>
                <ControlPoint>
                    <X>7211.5</X>
                    <Y>6811.5</Y>
                </ControlPoint>
            </ControlPoints>
            <PkTableDisplay>td3</PkTableDisplay>
            <FkTableDisplay>td17</FkTableDisplay>
            <Reference>r20</Reference>
        </ReferenceDisplay>
        <ReferenceDisplay Id="rd21">
            <Color>#000000</Color>
            <Type>Horizontal_4CP</Type>
            <ControlPoints>
                <ControlPoint>
                    <X>6926.5</X>
                    <Y>6893.5</Y>
                </ControlPoint>
                <ControlPoint>
                    <X>7116.5</X>
                    <Y>6893.5</Y>
                </ControlPoint>
                <ControlPoint>
                    <X>7116.5</X>
                    <Y>6801.5</Y>
                </ControlPoint>
                <ControlPoint>
                    <X>7195.5</X>
                    <Y>6801.5</Y>
                </ControlPoint>
            </ControlPoints>
            <PkTableDisplay>td1</PkTableDisplay>
            <FkTableDisplay>td17</FkTableDisplay>
            <Reference>r21</Reference>
        </ReferenceDisplay>
        <ReferenceDisplay Id="rd23">
            <Color>#000000</Color>
            <Type>Cross_3CP</Type>
            <ControlPoints>
                <ControlPoint>
                    <X>6911.5</X>
                    <Y>6734.5</Y>
                </ControlPoint>
                <ControlPoint>
                    <X>6911.5</X>
                    <Y>6583.5</Y>
                </ControlPoint>
                <ControlPoint>
                    <X>6780.5</X>
                    <Y>6583.5</Y>
                </ControlPoint>
            </ControlPoints>
            <PkTableDisplay>td2</PkTableDisplay>
            <FkTableDisplay>td20</FkTableDisplay>
            <Reference>r23</Reference>
        </ReferenceDisplay>
        <ReferenceDisplay Id="rd24">
            <Color>#000000</Color>
            <Type>Cross_3CP</Type>
            <ControlPoints>
                <ControlPoint>
                    <X>6526.5</X>
                    <Y>6720.5</Y>
                </ControlPoint>
                <ControlPoint>
                    <X>6526.5</X>
                    <Y>6572.5</Y>
                </ControlPoint>
                <ControlPoint>
                    <X>6704.5</X>
                    <Y>6572.5</Y>
                </ControlPoint>
            </ControlPoints>
            <PkTableDisplay>td10</PkTableDisplay>
            <FkTableDisplay>td20</FkTableDisplay>
            <Reference>r24</Reference>
        </ReferenceDisplay>
        <ReferenceDisplay Id="rd25">
            <Color>#000000</Color>
            <Type>Vertical_4CP</Type>
            <ControlPoints>
                <ControlPoint>
                    <X>7433.5</X>
                    <Y>7275.5</Y>
                </ControlPoint>
                <ControlPoint>
                    <X>7433.5</X>
                    <Y>6703.5</Y>
                </ControlPoint>
                <ControlPoint>
                    <X>6996.5</X>
                    <Y>6703.5</Y>
                </ControlPoint>
                <ControlPoint>
                    <X>6996.5</X>
                    <Y>6721.5</Y>
                </ControlPoint>
            </ControlPoints>
            <PkTableDisplay>td7</PkTableDisplay>
            <FkTableDisplay>td2</FkTableDisplay>
            <Reference>r25</Reference>
        </ReferenceDisplay>
        <ReferenceDisplay Id="rd26">
            <Color>#000000</Color>
            <Type>Cross_3CP</Type>
            <ControlPoints>
                <ControlPoint>
                    <X>7139.5</X>
                    <Y>6583.5</Y>
                </ControlPoint>
                <ControlPoint>
                    <X>6998.5</X>
                    <Y>6583.5</Y>
                </ControlPoint>
                <ControlPoint>
                    <X>6998.5</X>
                    <Y>6729.5</Y>
                </ControlPoint>
            </ControlPoints>
            <PkTableDisplay>td5</PkTableDisplay>
            <FkTableDisplay>td2</FkTableDisplay>
            <Reference>r26</Reference>
        </ReferenceDisplay>
        <ReferenceDisplay Id="rd27">
            <Color>#000000</Color>
            <Type>Self_5CP</Type>
            <ControlPoints>
                <ControlPoint>
                    <X>6478.5</X>
                    <Y>6982.5</Y>
                </ControlPoint>
                <ControlPoint>
                    <X>6478.5</X>
                    <Y>6924.5</Y>
                </ControlPoint>
                <ControlPoint>
                    <X>6357.5</X>
                    <Y>6924.5</Y>
                </ControlPoint>
                <ControlPoint>
                    <X>6357.5</X>
                    <Y>6990.5</Y>
                </ControlPoint>
                <ControlPoint>
                    <X>6473.5</X>
                    <Y>6990.5</Y>
                </ControlPoint>
            </ControlPoints>
            <PkTableDisplay>td9</PkTableDisplay>
            <FkTableDisplay>td9</FkTableDisplay>
            <Reference>r27</Reference>
        </ReferenceDisplay>
    </ReferenceDisplays>
    <Properties>
        <Property>
            <Name>pdf-printer-paper-size</Name>
            <Value>A4</Value>
        </Property>
        <Property>
            <Name>pdf-printer-margin-top</Name>
            <Value>10</Value>
        </Property>
        <Property>
            <Name>pdf-printer-margin-bottom</Name>
            <Value>10</Value>
        </Property>
        <Property>
            <Name>pdf-printer-margin-left</Name>
            <Value>10</Value>
        </Property>
        <Property>
            <Name>pdf-printer-margin-right</Name>
            <Value>10</Value>
        </Property>
        <Property>
            <Name>pdf-printer-page-orientation</Name>
            <Value>landscape</Value>
        </Property>
        <Property>
            <Name>pdf-printer-show-pages</Name>
            <Value>false</Value>
        </Property>
        <Property>
            <Name>pdf-printer-include-footer</Name>
            <Value>true</Value>
        </Property>
        <Property>
            <Name>reference-notation</Name>
            <Value>crows-foot</Value>
        </Property>
        <Property>
            <Name>show-only-pk-fk</Name>
            <Value>false</Value>
        </Property>
        <Property>
            <Name>pages-line-color</Name>
            <Value>#CC0000</Value>
        </Property>
        <Property>
            <Name>show-grid</Name>
            <Value>false</Value>
        </Property>
        <Property>
            <Name>grid-color</Name>
            <Value>#D9D9D9</Value>
        </Property>
        <Property>
            <Name>grid-style</Name>
            <Value>solid</Value>
        </Property>
        <Property>
            <Name>grid-spacing</Name>
            <Value>2</Value>
        </Property>
        <Property>
            <Name>grid-spacing-units</Name>
            <Value>cm</Value>
        </Property>
        <Property>
            <Name>grid-subdivisions</Name>
            <Value>1</Value>
        </Property>
    </Properties>
    <DefaultAdditionalProperties>
        <Types>
            <Name>table</Name>
            <Properties/>
        </Types>
        <Types>
            <Name>column</Name>
            <Properties/>
        </Types>
        <Types>
            <Name>alternate_key</Name>
            <Properties/>
        </Types>
        <Types>
            <Name>index</Name>
            <Properties/>
        </Types>
        <Types>
            <Name>table_check</Name>
            <Properties/>
        </Types>
        <Types>
            <Name>trigger</Name>
            <Properties/>
        </Types>
        <Types>
            <Name>reference</Name>
            <Properties/>
        </Types>
        <Types>
            <Name>view</Name>
            <Properties/>
        </Types>
        <Types>
            <Name>sequence</Name>
            <Properties/>
        </Types>
        <Types>
            <Name>procedure</Name>
            <Properties/>
        </Types>
        <Types>
            <Name>all</Name>
            <Properties/>
        </Types>
        <Types>
            <Name>view_column</Name>
            <Properties/>
        </Types>
        <Types>
            <Name>primary_key</Name>
            <Properties/>
        </Types>
        <Types>
            <Name>materialized_view</Name>
            <Properties/>
        </Types>
        <Types>
            <Name>materialized_view_column</Name>
            <Properties/>
        </Types>
        <Types>
            <Name>external_table</Name>
            <Properties/>
        </Types>
        <Types>
            <Name>external_table_column</Name>
            <Properties/>
        </Types>
    </DefaultAdditionalProperties>
</DatabaseModel>
